SimpleCSVParser/__init__.py
simplecsvparser-1.0.1.dist-info/METADATA
simplecsvparser-1.0.1.dist-info/WHEEL
simplecsvparser-1.0.1.dist-info/licenses/LICENSE
simplecsvparser-1.0.1.dist-info/RECORD
