Metadata-Version: 2.1
Name: SimpleCSVParser
Version: 1.0.1
Summary: A simple package to parse CSV
Project-URL: Homepage, https://github.com/stifskere/SimpleCSVParser
Project-URL: Issues, https://github.com/stifskere/SimpleCSVParser/issues
Author-email: Memw1 <stifskere@gmail.com>
License-File: LICENSE
Classifier: License :: OSI Approved :: MIT License
Classifier: Operating System :: OS Independent
Classifier: Programming Language :: Python :: 3
Requires-Python: >=3.10
